{
  "generator": "NominalFuzzer",
  "name": "post-balanceTransfer-20240411163217923",
  "testInteractions": [
    {
      "requestMethod": "POST",
      "requestURL": "https://pal-test.adyen.com/pal/servlet/BalanceControl/v1/balanceTransfer",
      "requestHeaders": "Accept: application/json\n",
      "requestBody": "{\"amount\": {\"currency\": \"6a5aee5f-5f99-4fa1-abc1-f868bdfeb1fc\", \"value\": 94}, \"fromMerchant\": \"Elke\", \"toMerchant\": \"2016/03/05\", \"type\": \"tax\"}",
      "requestSentAt": "Apr 11, 2024, 4:32:18 PM",
      "responseProtocol": "h2",
      "responseStatusCode": {
        "code": 401
      },
      "responseHeaders": "traceparent: 00-91c3c8efc8b4eaa65d82b129a1791987-d81f9dcbb2fa8335-01\nset-cookie: ██\nwww-authenticate: BASIC realm\u003d\"Adyen PAL Service Authentication\"\ncontent-type: application/json;charset\u003dutf-8\ndate: Thu, 11 Apr 2024 20:32:18 GMT\n",
      "responseBody": "{\"status\":401,\"errorCode\":\"000\",\"message\":\"HTTP Status Response - Unauthorized\",\"errorType\":\"security\"}",
      "responseReceivedAt": "Apr 11, 2024, 4:32:18 PM",
      "tags": []
    }
  ],
  "generatedAt": "Apr 11, 2024, 4:32:17 PM",
  "testResults": {
    "StatusCodeOracle": {
      "result": "UNKNOWN",
      "message": "The obtained status code is not informative enough to determine the outcome of the test sequence."
    }
  },
  "tags": []
}