{
  "generator": "NominalFuzzer",
  "name": "POST-/originKeys-20240411163610288",
  "testInteractions": [
    {
      "requestMethod": "POST",
      "requestURL": "https://checkout-test.adyen.com/v1/originKeys",
      "requestHeaders": "Accept: application/json\n",
      "requestBody": "{\"originDomains\": [\"madderish\"]}",
      "requestSentAt": "Apr 11, 2024, 4:36:11 PM",
      "responseProtocol": "h2",
      "responseStatusCode": {
        "code": 401
      },
      "responseHeaders": "traceparent: 00-b04f3722b22f18774286308476d29aed-51366adb4986d505-01\nset-cookie: ██\nwww-authenticate: BASIC realm\u003d\"Adyen PAL Service Authentication\"\ncontent-type: application/json;charset\u003dutf-8\ndate: Thu, 11 Apr 2024 20:36:10 GMT\n",
      "responseBody": "{\"status\":401,\"errorCode\":\"000\",\"message\":\"HTTP Status Response - Unauthorized\",\"errorType\":\"security\"}",
      "responseReceivedAt": "Apr 11, 2024, 4:36:11 PM",
      "tags": []
    }
  ],
  "generatedAt": "Apr 11, 2024, 4:36:10 PM",
  "testResults": {
    "StatusCodeOracle": {
      "result": "UNKNOWN",
      "message": "The obtained status code is not informative enough to determine the outcome of the test sequence."
    }
  },
  "tags": []
}