{
  "generator": "NominalFuzzer",
  "name": "post-getCostEstimate-20240411163442987",
  "testInteractions": [
    {
      "requestMethod": "POST",
      "requestURL": "https://pal-test.adyen.com/pal/servlet/BinLookup/v54/getCostEstimate",
      "requestHeaders": "Accept: application/json\n",
      "requestBody": "{\"amount\": {\"currency\": \"HMP\", \"value\": 110}, \"merchantAccount\": \"woady\", \"merchantDetails\": {\"countryCode\": \"XP\"}}",
      "requestSentAt": "Apr 11, 2024, 4:34:44 PM",
      "responseProtocol": "h2",
      "responseStatusCode": {
        "code": 401
      },
      "responseHeaders": "traceparent: 00-5825bba5b81408579bccf27321262e21-88360b70069ee1dd-01\nset-cookie: ██\nwww-authenticate: BASIC realm\u003d\"Adyen PAL Service Authentication\"\ncontent-type: application/json;charset\u003dutf-8\ndate: Thu, 11 Apr 2024 20:34:43 GMT\n",
      "responseBody": "{\"status\":401,\"errorCode\":\"000\",\"message\":\"HTTP Status Response - Unauthorized\",\"errorType\":\"security\"}",
      "responseReceivedAt": "Apr 11, 2024, 4:34:44 PM",
      "tags": []
    }
  ],
  "generatedAt": "Apr 11, 2024, 4:34:42 PM",
  "testResults": {
    "StatusCodeOracle": {
      "result": "UNKNOWN",
      "message": "The obtained status code is not informative enough to determine the outcome of the test sequence."
    }
  },
  "tags": []
}